pulumi_foreman/__init__.py
pulumi_foreman/_inputs.py
pulumi_foreman/_utilities.py
pulumi_foreman/architecture.py
pulumi_foreman/computeprofile.py
pulumi_foreman/computeresource.py
pulumi_foreman/defaulttemplate.py
pulumi_foreman/domain.py
pulumi_foreman/environment.py
pulumi_foreman/get_architecture.py
pulumi_foreman/get_computeprofile.py
pulumi_foreman/get_computeresource.py
pulumi_foreman/get_defaulttemplate.py
pulumi_foreman/get_domain.py
pulumi_foreman/get_environment.py
pulumi_foreman/get_global_parameter.py
pulumi_foreman/get_hostgroup.py
pulumi_foreman/get_httpproxy.py
pulumi_foreman/get_image.py
pulumi_foreman/get_jobtemplate.py
pulumi_foreman/get_katello_content_credential.py
pulumi_foreman/get_katello_content_view.py
pulumi_foreman/get_katello_lifecycle_environment.py
pulumi_foreman/get_katello_product.py
pulumi_foreman/get_katello_repository.py
pulumi_foreman/get_katello_sync_plan.py
pulumi_foreman/get_media.py
pulumi_foreman/get_model.py
pulumi_foreman/get_operatingsystem.py
pulumi_foreman/get_parameter.py
pulumi_foreman/get_partitiontable.py
pulumi_foreman/get_policy.py
pulumi_foreman/get_provisioningtemplate.py
pulumi_foreman/get_puppetclass.py
pulumi_foreman/get_setting.py
pulumi_foreman/get_smartclassparameter.py
pulumi_foreman/get_smartproxy.py
pulumi_foreman/get_subnet.py
pulumi_foreman/get_templateinput.py
pulumi_foreman/get_templatekind.py
pulumi_foreman/get_user.py
pulumi_foreman/get_usergroup.py
pulumi_foreman/global_parameter.py
pulumi_foreman/host.py
pulumi_foreman/hostgroup.py
pulumi_foreman/httpproxy.py
pulumi_foreman/image.py
pulumi_foreman/jobtemplate.py
pulumi_foreman/katello_content_credential.py
pulumi_foreman/katello_content_view.py
pulumi_foreman/katello_lifecycle_environment.py
pulumi_foreman/katello_product.py
pulumi_foreman/katello_repository.py
pulumi_foreman/katello_sync_plan.py
pulumi_foreman/media.py
pulumi_foreman/model.py
pulumi_foreman/operatingsystem.py
pulumi_foreman/outputs.py
pulumi_foreman/override_value.py
pulumi_foreman-1.0.1.dist-info/METADATA
pulumi_foreman-1.0.1.dist-info/WHEEL
pulumi_foreman-1.0.1.dist-info/top_level.txt
pulumi_foreman-1.0.1.dist-info/RECORD
